billing_shared/__init__.py
billing_shared/types.py
billing_shared/db/__init__.py
billing_shared/db/helpers.py
billing_shared/db/models.py
billing_shared/db/schemas.py
practicum_billing_shared-0.1.13.dist-info/METADATA
practicum_billing_shared-0.1.13.dist-info/WHEEL
practicum_billing_shared-0.1.13.dist-info/top_level.txt
practicum_billing_shared-0.1.13.dist-info/RECORD
