Metadata-Version: 2.4
Name: practicum_billing_shared
Version: 0.1.13
Summary: Shared code for billing
Requires-Python: >=3.12
Requires-Dist: pydantic>=2.10.4
Requires-Dist: sqlalchemy>=2.0.41
Requires-Dist: asyncpg>=0.30.0
Requires-Dist: aio_pika>=9.5.7
